pretrain4keras/__init__.py
pretrain4keras/layers.py
pretrain4keras/snippets.py
pretrain4keras/models/__init__.py
pretrain4keras/models/bart.py
pretrain4keras/models/bert.py
pretrain4keras-0.0.8.dist-info/METADATA
pretrain4keras-0.0.8.dist-info/WHEEL
pretrain4keras-0.0.8.dist-info/top_level.txt
pretrain4keras-0.0.8.dist-info/RECORD
