Metadata-Version: 2.1
Name: pretrain4keras
Version: 0.0.8
Summary: 用tf.keras (TF2.0+) 的稳定API实现NLP预训练模型，例如BERT、BART等。
Home-page: https://github.com/mosluo/pretrain4keras.git
Author: mos_luo
Author-email: mos_luo@163.com
Classifier: Programming Language :: Python :: 3
Classifier: License :: OSI Approved :: MIT License
Classifier: Operating System :: OS Independent
